{
  "id": 2021356,
  "title": "קבוצה (כימיה)",
  "url": "https://he.wikipedia.org/wiki/%D7%A7%D7%91%D7%95%D7%A6%D7%94_(%D7%9B%D7%99%D7%9E%D7%99%D7%94)",
  "category": "כימיה",
  "length_chars": 2391,
  "text": "בכימיה, קבוצה או משפחה היא מקבץ טורי (קו אנכי) של יסודות שבטבלה המחזורית. קיימים 18 קבוצות שכאלה בטבלה, כאשר הטורים בבלוק f (שבין קבוצה 2 לקבוצה 3) הם חסרי מספר.\nכל היסודות באותה קבוצה הם בעלי תכונות פיזיקליות וכימיות דומות, היות שהם בעלי אותה כמות של אלקטרונים בקליפת הערכיות. מרבית התכונות האופייניות של יסוד כלשהו למעשה נובעות מכמות האלקטרונים בקליפת הערכיות.\nישנן שלוש שיטות למספור הקבוצות:\n\nהשיטה המודרנית של מספור מ-1 עד 18, שמומלצת לפי ארגון ה-IUPAC מאז שנת 1990.\nשיטת A-B, בה השתמש ארגון ה-IUPAC עד 1990 (היה בשימוש בעיקר באירופה).\nשיטת A-B-A, שהומלצה לפני 1990 על ידי ה-CAS.\nהשיטה לחילוק הטבלה ל-18 קבוצות מקובלת על פי רוב, אך קיימים כמה חילוקי דעות לגבי מיקומם של המימן וההליום ולגבי בלוק ה-f.\nלחלק מהקבוצות יש שם ייחודי משלהן, לדוגמה השם \"כלקוגנים\" מזוהה עם הקבוצה ה-16. ולחלק מן הקבוצות קוראים בשם היסוד הראשון בקבוצה, למשל קבוצת המנגן מזוהה עם הקבוצה ה-7.\n\n\n== שמות הקבוצות ==\nבמהלך ההיסטוריה נעשו שימושים בכמה סטים של שמות לקבוצות:\n\nבנוסף, קיימים כמה שמות שהוצעו במהלך השנים אך לא קיבלו הכרה עולמית כמו:\n\nמתכות נדיפות (volatile metals) לקבוצה 12.\nאיקוסגנים (icosagens) לקבוצה 13.\nקריסטלוגנים (crystallogens) לקבוצה 14.\nאדמנטוגנים (adamantogens) לקבוצה 14.\nמרילידים (merylides) לקבוצה 14.\nאירוגנים (aerogens) לקבוצה 18.\n\n\n== שיטת CAS ושיטת IUPAC הישנה ==\nבעבר היו נהוגות שתי שיטות למספור הקבוצות: שיטת CAS ושיטת IUPAC הישנה. שתי השיטות השתמשו גם בספרות (רומיות) וגם באותיות A ו-B. שתי השיטות היו זהות מבחינת הספרות, שציינו את דרגת החמצון הכי גבוהה שיכולה להיות ליסוד מקבוצה זאת, לדוגמה, לאשלגן (K) יש אלקטרון ערכיות אחד, ולכן הוא ממוקם בקבוצה 1, ולקלציום שני אלקטרוני ערכיות, ולכן הוא ממוקם בקבוצה 2. למרות הדמיון בספרות בין שתי השיטות, השימוש באותיות היה שונה בכל שיטה.\nבשיטת IUPAC הישנה השתמשו באות A ליסודות הנמצאים בשמאל הטבלה, ובאות B ליסודות הנמצאים בימין הטבלה. בעוד שבשיטת CAS השתמשו באות A ליסודות מהקבוצות העיקריות, ובאות B ליסודות מהקבוצות של מתכות המעבר. שיטת IUPAC הישנה הייתה נפוצה בעיקר באירופה, בעוד שיטת CAS הייתה נפוצה בעיקר באמריקה.\nשיטת IUPAC החדשה נוצרה על מנת להחליף את שתי השיטות הישנות, על מנת להפסיק את הבלבול שנוצר עקב זה שבשתי השיטות השתמשו באותן אותיות וספרות לציון קבוצות שונות. שיטת IUPAC החדשה לא משתמש כלל באותיות, והיא פשוט ממספרת את הקבוצות מ-1 עד 18 בסדר עולה. השיטה הוצעה לראשונה לציבור בשנת 1985, ובשנת 1990 היא הוכנסה באופן רשמי למונחון IUPAC.\n\n\n== ראו גם ==\nמחזור (כימיה)\nהטבלה המחזורית\nסדרה כימית\n\n\n== לקריאה נוספת ==\n\n\n== הערות שוליים ==",
  "source": "hewiki",
  "retrieved_at": "2026-04-20T07:15:15.591849+00:00"
}